LICENSE
MANIFEST.in
README.md
requirements.txt
setup.py
netportal/__init__.py
netportal/cmccweb.py
netportal/netportal.py
netportal/wifiman.py
netportal.egg-info/PKG-INFO
netportal.egg-info/SOURCES.txt
netportal.egg-info/dependency_links.txt
netportal.egg-info/entry_points.txt
netportal.egg-info/not-zip-safe
netportal.egg-info/requires.txt
netportal.egg-info/top_level.txt
netportal/chinanet/__init__.py
netportal/chinanet/chinanet.py
netportal/chinanet/js_rsa.js
netportal/chinanet/js_rsa.py